MANIFEST.in
README.rst
setup.py
aliyun_python_sdk_yundun_ds.egg-info/PKG-INFO
aliyun_python_sdk_yundun_ds.egg-info/SOURCES.txt
aliyun_python_sdk_yundun_ds.egg-info/dependency_links.txt
aliyun_python_sdk_yundun_ds.egg-info/requires.txt
aliyun_python_sdk_yundun_ds.egg-info/top_level.txt
aliyunsdkyundun_ds/__init__.py
aliyunsdkyundun_ds/request/__init__.py
aliyunsdkyundun_ds/request/v20190103/CreateConfigRequest.py
aliyunsdkyundun_ds/request/v20190103/CreateDataLimitRequest.py
aliyunsdkyundun_ds/request/v20190103/CreateRuleRequest.py
aliyunsdkyundun_ds/request/v20190103/CreateUserAuthRequest.py
aliyunsdkyundun_ds/request/v20190103/DeleteDataLimitRequest.py
aliyunsdkyundun_ds/request/v20190103/DeleteRuleRequest.py
aliyunsdkyundun_ds/request/v20190103/DescribeAccountDetailRequest.py
aliyunsdkyundun_ds/request/v20190103/DescribeAccountsRequest.py
aliyunsdkyundun_ds/request/v20190103/DescribeAuthAccountsRequest.py
aliyunsdkyundun_ds/request/v20190103/DescribeColumnsRequest.py
aliyunsdkyundun_ds/request/v20190103/DescribeConditionsRequest.py
aliyunsdkyundun_ds/request/v20190103/DescribeConfigsRequest.py
aliyunsdkyundun_ds/request/v20190103/DescribeDataAssetsRequest.py
aliyunsdkyundun_ds/request/v20190103/DescribeDataCountsRequest.py
aliyunsdkyundun_ds/request/v20190103/DescribeDataHubConnectorsRequest.py
aliyunsdkyundun_ds/request/v20190103/DescribeDataHubProjectsRequest.py
aliyunsdkyundun_ds/request/v20190103/DescribeDataHubSubscriptionsRequest.py
aliyunsdkyundun_ds/request/v20190103/DescribeDataHubTopicsRequest.py
aliyunsdkyundun_ds/request/v20190103/DescribeDataLimitSetRequest.py
aliyunsdkyundun_ds/request/v20190103/DescribeDataTotalCountRequest.py
aliyunsdkyundun_ds/request/v20190103/DescribeDepartCountsRequest.py
aliyunsdkyundun_ds/request/v20190103/DescribeDepartTotalCountRequest.py
aliyunsdkyundun_ds/request/v20190103/DescribeDepartsRequest.py
aliyunsdkyundun_ds/request/v20190103/DescribeEventCountsRequest.py
aliyunsdkyundun_ds/request/v20190103/DescribeEventDetailRequest.py
aliyunsdkyundun_ds/request/v20190103/DescribeEventTotalCountRequest.py
aliyunsdkyundun_ds/request/v20190103/DescribeEventTypesRequest.py
aliyunsdkyundun_ds/request/v20190103/DescribeEventsRequest.py
